kube_tests/__init__.py
kube_tests/adapter.py
kube_tests/client.py
kube_tests/iloader.py
kube_tests/iparser.py
kube_tests/job_builder.py
kube_tests/py.typed
kube_tests/template_compiler.py
kube_tests/utils.py
kube_tests/loaders/__init__.py
kube_tests/loaders/file_loader.py
kube_tests/loaders/py.typed
kube_tests/parsers/__init__.py
kube_tests/parsers/py.typed
kube_tests/parsers/yaml_parser.py
kube_tests-0.0.6.dist-info/METADATA
kube_tests-0.0.6.dist-info/WHEEL
kube_tests-0.0.6.dist-info/top_level.txt
kube_tests-0.0.6.dist-info/RECORD
